{
  "f.a.e.z.e.97": {
    "target": "9h"
  },
  "nil": {
    "target": "4h"
  },
  "Mobina": {
    "target": "8h"
  },
  "Mainak": {
    "target": "7h"
  },
  "yekta": {
    "target": "7h 30m"
  },
  "MahiSiah": {
    "target": "8h"
  },
  "Rira": {
    "target": "8h"
  },
  "yosanoriko": {
    "target": "12h"
  },
  "nzn_mr": {
    "target": "7h 30m"
  },
  "Durga": {
    "target": "7h"
  },
  "negin": {
    "target": "7h 30m"
  },
  "nazanin": {
    "target": "7h 30m"
  },
  "Aras": {
    "target": "4h"
  },
  "Shadi": {
    "target": "4h"
  },
  "mushroom": {
    "target": "6h"
  },
  "FAFA": {
    "target": "7h 30m"
  },
  "MEL": {
    "target": "4h"
  },
  "Azadeh": {
    "target": "4h"
  },
  "سارا": {
    "target": "7h 30m"
  },
  "moein": {
    "target": "8h"
  },
  "fatemeh": {
    "target": "7h 30m"
  },
  "saye": {
    "target": "5h"
  }
}
